ec_tools/__init__.py
ec_tools/data/__init__.py
ec_tools/data/data_object.py
ec_tools/data/json_type.py
ec_tools/database/__init__.py
ec_tools/database/kv_dao/__init__.py
ec_tools/database/kv_dao/cipher_kv_dao.py
ec_tools/database/kv_dao/kv_dao.py
ec_tools/database/kv_dao/kv_data.py
ec_tools/database/kv_dao/sqlite_kv_dao.py
ec_tools/database/sqlite_client/__init__.py
ec_tools/database/sqlite_client/sqlite_client.py
ec_tools/database/sqlite_client/sqlite_query.py
ec_tools/database/sqlite_dao/__init__.py
ec_tools/database/sqlite_dao/sqlite_dao.py
ec_tools/database/sqlite_dao/sqlite_data_object.py
ec_tools/database/sqlite_dao/sqlite_query_generator.py
ec_tools/tools/__init__.py
ec_tools/tools/headers_manager.py
ec_tools/tools/key_manager.py
ec_tools/tools/thread_pool.py
ec_tools/tools/cipher/__init__.py
ec_tools/tools/cipher/aes_cipher.py
ec_tools/tools/cipher/aes_config.py
ec_tools/tools/cipher/chunk_config.py
ec_tools/tools/cipher/chunk_encryption_utils.py
ec_tools/tools/cipher/cipher.py
ec_tools/tools/cipher/file_encryption_utils.py
ec_tools/tools/cipher/password_tool.py
ec_tools/tools/cipher/cipher_generator/__init__.py
ec_tools/tools/cipher/cipher_generator/aes_cipher_generator.py
ec_tools/tools/cipher/cipher_generator/cipher_generator.py
ec_tools/utils/__init__.py
ec_tools/utils/hash_utils.py
ec_tools/utils/io_utils.py
ec_tools/utils/misc.py
ec_tools/utils/os_utils.py
ec_tools/utils/timer.py
ec_tools-2.8.dist-info/METADATA
ec_tools-2.8.dist-info/WHEEL
ec_tools-2.8.dist-info/top_level.txt
ec_tools-2.8.dist-info/RECORD
