Metadata-Version: 2.4
Name: ec_tools
Version: 2.8
Summary: EC Tools
Classifier: Programming Language :: Python :: 3
Classifier: License :: OSI Approved :: MIT License
Requires-Python: >=3.11
Requires-Dist: dataclasses
Requires-Dist: typing
Dynamic: classifier
Dynamic: requires-dist
Dynamic: requires-python
Dynamic: summary
